nexus_env/__init__.py
nexus_env/env.py
nexus_env/callbacks/__init__.py
nexus_env/callbacks/hf_upload_callback.py
nexus_env/callbacks/model_card.py
nexus_env/callbacks/save_model_callback.py
nexus_env/callbacks/wandb_callback.py
nexus_env/static/index.html
nexus_env/static/vite.svg
nexus_env/static/vite.svg.import
nexus_env/static/assets/index-CzTNmq5q.js
nexus_env/static/assets/index-DQ3P1g1z.css
nexus_env/utils/__init__.py
nexus_env/utils/hydra_loader.py
nexus_gym-0.1.0.dist-info/METADATA
nexus_gym-0.1.0.dist-info/WHEEL
nexus_gym-0.1.0.dist-info/entry_points.txt
nexus_gym-0.1.0.dist-info/top_level.txt
nexus_gym-0.1.0.dist-info/RECORD
